mcp_server_yfinance/__main__.py
mcp_server_yfinance/_version.py
mcp_server_yfinance-0.1.0.dev44.dist-info/METADATA
mcp_server_yfinance-0.1.0.dev44.dist-info/WHEEL
mcp_server_yfinance-0.1.0.dev44.dist-info/entry_points.txt
mcp_server_yfinance-0.1.0.dev44.dist-info/licenses/LICENSE
mcp_server_yfinance-0.1.0.dev44.dist-info/RECORD
