Metadata-Version: 2.4
Name: mcp-server-yfinance
Version: 0.1.0.dev44
Summary: A Model Context Protocol (MCP) server for agentic retrieval of financial market data. This server leverages YFinance to provide a simple and efficient way to access historical stock prices, dividends, stock splits, company information, and other financial metrics.
Project-URL: Homepage, https://github.com/danchev/openmarkets
Project-URL: Issues, https://github.com/danchev/openmarkets/issues
Author-email: Dobri Danchev <python-dist@danchev.net>
License: AGPL-3.0-or-later
License-File: LICENSE
Keywords: finance,financial data retrieval,investment,machinelearning,mcp,modelcontextprotocol,yahoo finance
Classifier: Development Status :: 3 - Alpha
Classifier: Intended Audience :: Developers
Classifier: Intended Audience :: Financial and Insurance Industry
Classifier: License :: OSI Approved :: GNU Affero General Public License v3 or later (AGPLv3+)
Classifier: Operating System :: OS Independent
Classifier: Programming Language :: Python :: 3 :: Only
Classifier: Programming Language :: Python :: 3.11
Classifier: Programming Language :: Python :: 3.12
Classifier: Programming Language :: Python :: 3.13
Classifier: Programming Language :: Python :: 3.14
Classifier: Topic :: Office/Business :: Financial
Classifier: Topic :: Office/Business :: Financial :: Investment
Classifier: Topic :: Scientific/Engineering
Classifier: Topic :: Scientific/Engineering :: Artificial Intelligence
Classifier: Topic :: Scientific/Engineering :: Interface Engine/Protocol Translator
Classifier: Topic :: Software Development :: Libraries
Classifier: Topic :: Software Development :: Libraries :: Python Modules
Requires-Python: >=3.11
Requires-Dist: openmarkets>=0.1.0.dev53
